hestia/__init__.py
hestia/clustering.py
hestia/dataset_generator.py
hestia/partition.py
hestia/reduction.py
hestia/similarity.py
hestia/utils/__init__.py
hestia/utils/bulk_similarity_metrics.py
hestia/utils/dataset_utils.py
hestia/utils/file_format.py
hestia/utils/graph_part_utils.py
hestia/utils/label_balance.py
hestia/utils/mmseqs_fake_prefilter.sh
hestia_ood-0.0.36.data/data/mmseqs_fake_prefilter.sh
hestia_ood-0.0.36.dist-info/LICENSE
hestia_ood-0.0.36.dist-info/METADATA
hestia_ood-0.0.36.dist-info/WHEEL
hestia_ood-0.0.36.dist-info/top_level.txt
hestia_ood-0.0.36.dist-info/RECORD
