Metadata-Version: 2.2
Name: hestia-ood
Version: 0.0.36
Summary: Suite of tools for analysing the independence between training and evaluation biosequence datasets and to generate new generalisation-evaluating hold-out partitions
Home-page: https://github.com/IBM/Hestia-GOOD
Author: Raul Fernandez-Diaz
Author-email: raul.fernandezdiaz@ucdconnect.ie
License: MIT
Keywords: hestia
Requires-Python: >=3.9
License-File: LICENSE
Requires-Dist: networkx
Requires-Dist: scipy
Requires-Dist: scikit-learn
Requires-Dist: pandas
Requires-Dist: polars
Requires-Dist: numpy
Requires-Dist: tqdm
Dynamic: author
Dynamic: author-email
Dynamic: description
Dynamic: description-content-type
Dynamic: home-page
Dynamic: keywords
Dynamic: license
Dynamic: requires-dist
Dynamic: requires-python
Dynamic: summary
